exponent/__init__.py
exponent/main.py
exponent/cli/__init__.py
exponent/cli/commands/__init__.py
exponent/cli/commands/analyze.py
exponent/cli/commands/deploy.py
exponent/cli/commands/init.py
exponent/cli/commands/interactive.py
exponent/cli/commands/train.py
exponent/cli/commands/upload_dataset.py
exponent/core/__init__.py
exponent/core/auth.py
exponent/core/code_gen.py
exponent/core/config.py
exponent/core/error_agent.py
exponent/core/github_utils.py
exponent/core/modal_runner.py
exponent/core/s3_utils.py
exponent_ml-0.1.1.dist-info/METADATA
exponent_ml-0.1.1.dist-info/WHEEL
exponent_ml-0.1.1.dist-info/entry_points.txt
exponent_ml-0.1.1.dist-info/top_level.txt
exponent_ml-0.1.1.dist-info/RECORD
