Metadata-Version: 2.4
Name: exponent-ml
Version: 0.1.1
Summary: Claude Code for ML developers. Build and deploy ML models from your terminal. Accelerate your ML pipeline with Exponent.
Author-email: Eden Etuk <edens.etuk@gmail.com>
Maintainer-email: Eden Etuk <edens.etuk@gmail.com>
License: MIT
Project-URL: Homepage, https://github.com/3d3n-ops/exponent-0.1
Project-URL: Repository, https://github.com/3d3n-ops/exponent-0.1
Project-URL: Documentation, https://exponent-ml.vercel.app/docs
Project-URL: Issues, https://github.com/3d3n-ops/exponent-0.1/issues
Keywords: machine-learning,cli,ai,ml,automation,modal,anthropic
Classifier: Development Status :: 4 - Beta
Classifier: Intended Audience :: Developers
Classifier: Intended Audience :: Science/Research
Classifier: License :: OSI Approved :: MIT License
Classifier: Operating System :: OS Independent
Classifier: Programming Language :: Python :: 3
Classifier: Programming Language :: Python :: 3.8
Classifier: Programming Language :: Python :: 3.9
Classifier: Programming Language :: Python :: 3.10
Classifier: Programming Language :: Python :: 3.11
Classifier: Programming Language :: Python :: 3.12
Classifier: Topic :: Scientific/Engineering :: Artificial Intelligence
Classifier: Topic :: Software Development :: Libraries :: Python Modules
Classifier: Topic :: Software Development :: Libraries :: Application Frameworks
Requires-Python: >=3.8
Requires-Dist: typer>=0.9.0
Requires-Dist: anthropic>=0.7.0
Requires-Dist: boto3>=1.26.0
Requires-Dist: pandas>=1.5.0
Requires-Dist: numpy>=1.21.0
Requires-Dist: modal>=0.55.0
Requires-Dist: PyGithub>=1.59.0
Requires-Dist: python-dotenv>=1.0.0
Requires-Dist: inquirer>=3.1.0
Requires-Dist: scikit-learn>=1.3.0
Requires-Dist: matplotlib>=3.5.0
Requires-Dist: seaborn>=0.11.0
Requires-Dist: clerk-sdk-python>=0.1.0
Requires-Dist: requests>=2.28.0
Requires-Dist: rich>=13.0.0
Provides-Extra: dev
Requires-Dist: pytest>=7.0.0; extra == "dev"
Requires-Dist: pytest-cov>=4.0.0; extra == "dev"
Requires-Dist: black>=22.0.0; extra == "dev"
Requires-Dist: isort>=5.0.0; extra == "dev"
Requires-Dist: flake8>=5.0.0; extra == "dev"
Requires-Dist: mypy>=1.0.0; extra == "dev"
Requires-Dist: pre-commit>=3.0.0; extra == "dev"
Provides-Extra: docs
Requires-Dist: sphinx>=6.0.0; extra == "docs"
Requires-Dist: sphinx-rtd-theme>=1.0.0; extra == "docs"
Requires-Dist: myst-parser>=1.0.0; extra == "docs"
